quantsumore/__crypto_config.py
quantsumore/__init__.py
quantsumore/__os_config.py
quantsumore/__stock_config.py
quantsumore/__user_agents_config.py
quantsumore/_version.py
quantsumore/date_parser.py
quantsumore/exceptions.py
quantsumore/strata_utils.py
quantsumore/sys_utils.py
quantsumore/web_utils.py
quantsumore/_http/__init__.py
quantsumore/_http/connection.py
quantsumore/_http/response_utils.py
quantsumore/_http/utils.py
quantsumore/analysis/__init__.py
quantsumore/analysis/_fa.py
quantsumore/analysis/_frameworks.py
quantsumore/analysis/fundamental.py
quantsumore/analysis/technical.py
quantsumore/api/__init__.py
quantsumore/api/market_utils.py
quantsumore/api/parse_tools.py
quantsumore/api/prep.py
quantsumore/api/shape_tools.py
quantsumore/api/cpi/ConsumerPriceIndexAPI.py
quantsumore/api/cpi/__init__.py
quantsumore/api/cpi/parse/__init__.py
quantsumore/api/cpi/parse/cpi.py
quantsumore/api/crypto/CryptoAPI.py
quantsumore/api/crypto/__init__.py
quantsumore/api/crypto/parse/__init__.py
quantsumore/api/crypto/parse/crypto.py
quantsumore/api/equity/EquityAPI.py
quantsumore/api/equity/__init__.py
quantsumore/api/equity/parse/__init__.py
quantsumore/api/equity/parse/dividend.py
quantsumore/api/equity/parse/fin_statement.py
quantsumore/api/equity/parse/stock.py
quantsumore/api/forex/ForexAPI.py
quantsumore/api/forex/__init__.py
quantsumore/api/forex/parse/__init__.py
quantsumore/api/forex/parse/fx.py
quantsumore/api/treasury/TreasuryAPI.py
quantsumore/api/treasury/__init__.py
quantsumore/api/treasury/parse/__init__.py
quantsumore/api/treasury/parse/trates.py
quantsumore/files/os_versions.json
quantsumore/files/stock_tickers.txt
quantsumore/files/user_agents.json
quantsumore/files/crypto/all_data.json
quantsumore/files/crypto/cryptocurrency.json
quantsumore/files/crypto/exchanges.json
quantsumore/files/crypto/pairs.json
quantsumore/gui/__init__.py
quantsumore/gui/assets/__init__.py
quantsumore/gui/assets/icon.ico
quantsumore/gui/assets/icon.png
quantsumore-2.1.5b1.dist-info/METADATA
quantsumore-2.1.5b1.dist-info/WHEEL
quantsumore-2.1.5b1.dist-info/top_level.txt
quantsumore-2.1.5b1.dist-info/RECORD
