Metadata-Version: 2.1
Name: quantsumore
Version: 2.1.5b1
Summary: A comprehensive Python library for scraping and retrieving real-time data across multiple financial markets, including cryptocurrencies, equities, Forex, treasury yields, and consumer price index (CPI) data.
Home-page: https://github.com/cedricmoorejr/quantsumore/tree/v2.1.5b1
Author: Cedric Moore Jr.
Author-email: cedricmoorejunior5@gmail.com
License: Apache Software License
Project-URL: Source Code, https://github.com/cedricmoorejr/quantsumore/releases/tag/v2.1.5-beta.1
Classifier: Programming Language :: Python :: 3
Classifier: License :: OSI Approved :: Apache Software License
Classifier: Operating System :: Microsoft :: Windows
Classifier: Operating System :: POSIX :: Linux
Classifier: Operating System :: MacOS :: MacOS X
Classifier: Development Status :: 4 - Beta
Classifier: Intended Audience :: Developers
Classifier: Natural Language :: English
Classifier: Programming Language :: Python :: 3.8
Classifier: Programming Language :: Python :: 3.9
Classifier: Programming Language :: Python :: 3.10
Requires-Python: >=3.8
Requires-Dist: openpyxl
Requires-Dist: pandas
Requires-Dist: requests
Requires-Dist: matplotlib
Requires-Dist: pillow
Requires-Dist: numpy
Requires-Dist: requests-cache
Requires-Dist: bs4
Requires-Dist: lxml
Requires-Dist: importlib-resources ; python_version < "3.9"
